README.rst
setup.cfg
setup.py
auxi.egg-info/PKG-INFO
auxi.egg-info/SOURCES.txt
auxi.egg-info/dependency_links.txt
auxi.egg-info/requires.txt
auxi.egg-info/top_level.txt
src/__init__.py
src/tests.py
src/../CONTRIBUTING.md
src/../LICENSE.md
src/../MAKING-RELEASES.md
src/../RELEASE-NOTES.md
src/../ROLES.md
src/../STANDARDS.md
src/core/__init__.py
src/core/bibliography.py
src/core/bibliography_test.py
src/core/helpers.py
src/core/helpers_test.py
src/core/objects.py
src/core/objects_test.py
src/core/reporting.py
src/core/reporting_test.py
src/core/time.py
src/core/time_test.py
src/doc/auxiUserManual.pdf
src/examples/courier_example.py
src/examples/readme
src/examples/readme.ipynb
src/examples/modelling/readme
src/examples/temp/dataset-auxiite.csv
src/examples/tools/materialphysicalproperties/core.Dataset.ipynb
src/examples/tools/materialphysicalproperties/idealgas.ipynb
src/examples/tools/materialphysicalproperties/slags.ipynb
src/examples/tools/materialphysicalproperties/data/readme
src/examples/tools/transportphenomena/heattransfer/naturalconvection.IsothermalFlatSurface.ipynb
src/modelling/__init__.py
src/modelling/business/__init__.py
src/modelling/business/basic.py
src/modelling/business/basic_test.py
src/modelling/business/models.py
src/modelling/business/models_test.py
src/modelling/business/structure.py
src/modelling/business/structure_test.py
src/modelling/financial/__init__.py
src/modelling/financial/des.py
src/modelling/financial/des_test.py
src/modelling/financial/reporting.py
src/modelling/financial/reporting_test.py
src/modelling/process/__init__.py
src/modelling/process/materials/__init__.py
src/modelling/process/materials/chem.py
src/modelling/process/materials/chem_test.py
src/modelling/process/materials/core.py
src/modelling/process/materials/core_test.py
src/modelling/process/materials/psd.py
src/modelling/process/materials/psd_test.py
src/modelling/process/materials/slurry.py
src/modelling/process/materials/slurry_test.py
src/modelling/process/materials/thermo.py
src/modelling/process/materials/thermo_test.py
src/modelling/process/materials/data/chemmaterial.test.ilmenite.txt
