Metadata-Version: 1.1
Name: auxi
Version: 0.3.3
Summary: A toolkit to help metallurgical process engineers to rapidly do day-to-day calculations.
Home-page: https://github.com/Ex-Mente/auxi.0
Author: Ex Mente (Pty) Ltd
Author-email: dev@ex-mente.co.za
License: LGPL v3.0
Download-URL: https://pypi.python.org/pypi/auxi
Keywords: metallurgy,chemistry,modelling,simulation,thermochemistry,engineering,mass balance,energy balance
Platform: Ubunutu 14.04
Platform: Ubuntu 15.04
Platform: Windows 7 (For the stoichiometry and thermochemistry tools only.)
